airflowscan/__init__.py
airflowscan/cli.py
airflowscan/data/CHECKLIST.md
airflowscan/data/airflow_cfg.schema
airflowscan/data/default_airflow.cfg
airflowscan/data/hardened_airflow.cfg
airflowscan-0.1.3.1.dist-info/LICENSE
airflowscan-0.1.3.1.dist-info/METADATA
airflowscan-0.1.3.1.dist-info/WHEEL
airflowscan-0.1.3.1.dist-info/entry_points.txt
airflowscan-0.1.3.1.dist-info/top_level.txt
airflowscan-0.1.3.1.dist-info/RECORD
