Metadata-Version: 2.1
Name: airflowscan
Version: 0.1.3.1
Summary: Static analysis tool to check Airflow configuration files for insecure settings
Home-page: https://github.com/nightwatchcybersecurity/airflowscan
Author: Nightwatch Cybersecurity
Author-email: research@nightwatchcybersecurity.com
License: GNU
Project-URL: Bug Reports, https://github.com/nightwatchcybersecurity/airflowscan/issues
Project-URL: Source, https://github.com/nightwatchcybersecurity/airflowscan
Platform: UNKNOWN
Classifier: Environment :: Console
Classifier: Development Status :: 3 - Alpha
Classifier: License :: OSI Approved :: Apache Software License
Classifier: Operating System :: OS Independent
Classifier: Programming Language :: Python :: 3.5
Classifier: Programming Language :: Python :: 3.6
Classifier: Programming Language :: Python :: 3.7
Requires-Python: >=3.5
Requires-Dist: anymarkup (>=0.8.0)
Requires-Dist: click (>=7.0)
Requires-Dist: jsonschema (>=3.0.1)
Requires-Dist: pytest (>=5.0.0)
Requires-Dist: pytest-cov (>=2.7.1)
